jotts/__init__.py
jotts/jotts.py
jotts/synthesizer/__init__.py
jotts/synthesizer/audio.py
jotts/synthesizer/hparams.py
jotts/synthesizer/inference.py
jotts/synthesizer/models/__init__.py
jotts/synthesizer/models/tacotron.py
jotts/synthesizer/utils/__init__.py
jotts/synthesizer/utils/cleaners.py
jotts/synthesizer/utils/numbers.py
jotts/synthesizer/utils/symbols.py
jotts/synthesizer/utils/text.py
jotts/vocoder/__init__.py
jotts/vocoder/audio.py
jotts/vocoder/display.py
jotts/vocoder/distribution.py
jotts/vocoder/hparams.py
jotts/vocoder/inference.py
jotts/vocoder/models/__init__.py
jotts/vocoder/models/fatchord_version.py
jotts-1.0.5.dist-info/LICENSE
jotts-1.0.5.dist-info/METADATA
jotts-1.0.5.dist-info/WHEEL
jotts-1.0.5.dist-info/top_level.txt
jotts-1.0.5.dist-info/RECORD
