Metadata-Version: 2.1
Name: jotts
Version: 1.0.5
Summary: JoTTS is a German text-to-speech engine.
Home-page: https://github.com/padmalcom/jotts
Author: Jonas Freiknecht
Author-email: j.freiknecht@googlemail.com
License: MIT
Platform: UNKNOWN
Classifier: Development Status :: 4 - Beta
Classifier: Intended Audience :: Developers
Classifier: License :: OSI Approved :: MIT License
Classifier: Operating System :: OS Independent
Classifier: Programming Language :: Python :: 3.6
Classifier: Programming Language :: Python :: 3.7
Classifier: Programming Language :: Python :: 3.8
Classifier: Programming Language :: Python :: 3.9
Classifier: Programming Language :: Python :: 3.10
Requires-Python: >=3.6
License-File: LICENSE
Requires-Dist: appdirs (==1.4.4)
Requires-Dist: audioread (==3.0.0)
Requires-Dist: cffi (==1.15.0)
Requires-Dist: charset-normalizer (==2.1.1)
Requires-Dist: colorama (==0.4.6)
Requires-Dist: contourpy (==1.0.6)
Requires-Dist: cycler (==0.11.0)
Requires-Dist: decorator (==5.1.1)
Requires-Dist: fonttools (==4.38.0)
Requires-Dist: idna (==3.4)
Requires-Dist: inflect (==6.0.2)
Requires-Dist: joblib (==1.2.0)
Requires-Dist: kiwisolver (==1.4.4)
Requires-Dist: librosa (==0.9.2)
Requires-Dist: llvmlite (==0.39.1)
Requires-Dist: loguru (==0.6.0)
Requires-Dist: matplotlib (==3.6.2)
Requires-Dist: numba (==0.56.4)
Requires-Dist: numpy (>=1.23.4)
Requires-Dist: packaging (==21.3)
Requires-Dist: Pillow (==9.3.0)
Requires-Dist: pooch (==1.6.0)
Requires-Dist: pycparser (==2.21)
Requires-Dist: pydantic (==1.10.2)
Requires-Dist: pyparsing (==3.0.9)
Requires-Dist: python-dateutil (==2.8.2)
Requires-Dist: requests (==2.28.1)
Requires-Dist: resampy (==0.4.2)
Requires-Dist: scikit-learn (==1.1.3)
Requires-Dist: scipy (>=1.9.3)
Requires-Dist: six (==1.16.0)
Requires-Dist: sounddevice (==0.4.5)
Requires-Dist: soundfile (==0.11.0)
Requires-Dist: threadpoolctl (==3.1.0)
Requires-Dist: torch (>=1.10.0)
Requires-Dist: tqdm (>=4.64.1)
Requires-Dist: typing-extensions (==4.4.0)
Requires-Dist: Unidecode (==1.3.6)
Requires-Dist: urllib3 (==1.26.12)
